mcp_docs-0.0.1.dist-info/licenses/LICENSE
src/__init__.py
src/cli.py
src/config.py
src/embeddings/__init__.py
src/embeddings/azure_openai_provider.py
src/embeddings/openai_provider.py
src/embeddings/provider.py
src/indexer/__init__.py
src/indexer/chunker.py
src/indexer/cleaner.py
src/indexer/db_writer.py
src/indexer/embedder.py
src/indexer/scrapper.py
src/utils/__init__.py
src/utils/url_filter.py
src/vectorstores/__init__.py
src/vectorstores/chrome_store.py
src/vectorstores/store.py
mcp_docs-0.0.1.dist-info/METADATA
mcp_docs-0.0.1.dist-info/WHEEL
mcp_docs-0.0.1.dist-info/entry_points.txt
mcp_docs-0.0.1.dist-info/top_level.txt
mcp_docs-0.0.1.dist-info/RECORD
