Metadata-Version: 2.4
Name: mcp-docs
Version: 0.0.1
Summary: Turn any documentation site into an MCP server
Author: mcp-docs contributors
License: MIT
Keywords: mcp,documentation,indexing,vector-search,embeddings,chromadb
Classifier: Development Status :: 3 - Alpha
Classifier: Intended Audience :: Developers
Classifier: License :: OSI Approved :: MIT License
Classifier: Programming Language :: Python :: 3
Classifier: Programming Language :: Python :: 3.8
Classifier: Programming Language :: Python :: 3.9
Classifier: Programming Language :: Python :: 3.10
Classifier: Programming Language :: Python :: 3.11
Classifier: Programming Language :: Python :: 3.12
Classifier: Topic :: Software Development :: Libraries :: Python Modules
Classifier: Topic :: Documentation
Requires-Python: >=3.8
License-File: LICENSE
Requires-Dist: typer>=0.9.0
Requires-Dist: chromadb>=0.5.5
Requires-Dist: openai>=1.28.0
Requires-Dist: playwright>=1.40.0
Requires-Dist: beautifulsoup4>=4.12.3
Requires-Dist: requests>=2.32.3
Requires-Dist: python-dotenv>=1.0.0
Requires-Dist: mcp>=0.1.0
Requires-Dist: numpy>=1.24.0
Requires-Dist: lxml>=5.3.0
Requires-Dist: html2text>=2024.2.26
Requires-Dist: markdown>=3.6
Provides-Extra: dev
Requires-Dist: pytest>=7.0.0; extra == "dev"
Requires-Dist: black>=23.0.0; extra == "dev"
Requires-Dist: ruff>=0.1.0; extra == "dev"
Dynamic: license-file
